day4/shift_reg4.v
module shift_reg4(
    input clk,
    input rst,       // synchronous reset, active high
    input shift_in,  // new bit coming in each cycle
    output reg [3:0] q
);
    always @(posedge clk) begin
        if (rst) q <= 4'b0;
        else q <= {q[2:0], shift_in};
    end
endmodule

day4/shift_reg4_tb.v
// shift_reg4_tb.v
`timescale 1ns/1ps

module shift_reg4_tb;
    reg        clk, rst, shift_in;
    wire [3:0] q;

    shift_reg4 uut (
        .clk(clk),
        .rst(rst),
        .shift_in(shift_in),
        .q(q)
    );

    // generate a clock: toggle every 5ns -> 10ns period
    always #5 clk = ~clk;

    task check(input [3:0] expected);
        begin
            @(posedge clk); #1; // sample just after the clock edge
            if (q !== expected)
                $display("FAIL: got q=%b, expected %b", q, expected);
            else
                $display("PASS: q=%b", q);
        end
    endtask

    initial begin
        $dumpfile("shift_reg4.vcd");
        $dumpvars(0, shift_reg4_tb);

        clk = 0; rst = 1; shift_in = 0;
        @(posedge clk); #1;
        if (q !== 4'b0000) $display("FAIL: reset didn't clear q, got %b", q);
        else $display("PASS: reset -> q=0000");

        rst = 0;

        // shift in the pattern 1,0,1,1 one bit per cycle, check q after each
        shift_in = 1; check(4'b0001);
        shift_in = 0; check(4'b0010);
        shift_in = 1; check(4'b0101);
        shift_in = 1; check(4'b1011);

        // one more shift should drop the oldest bit off the top
        shift_in = 0; check(4'b0110);

        $finish;
    end
endmodule

day4/shift_reg4.vcd
$date
	Thu Sep 10 19:33:22 2026
$end
$version
	Icarus Verilog
$end
$timescale
	1ps
$end
$scope module shift_reg4_tb $end
$var wire 4 ! q [3:0] $end
$var reg 1 " clk $end
$var reg 1 # rst $end
$var reg 1 $ shift_in $end
$scope module uut $end
$var wire 1 " clk $end
$var wire 1 # rst $end
$var wire 1 $ shift_in $end
$var reg 4 % q [3:0] $end
$upscope $end
$scope task check $end
$var reg 4 & expected [3:0] $end
$upscope $end
$upscope $end
$enddefinitions $end
$comment Show the parameter values. $end
$dumpall
$end
#0
$dumpvars
bx &
bx %
0$
1#
0"
bx !
$end
#5000
b0 !
b0 %
1"
#6000
b1 &
1$
0#
#10000
0"
#15000
b1 !
b1 %
1"
#16000
b10 &
0$
#20000
0"
#25000
b10 !
b10 %
1"
#26000
b101 &
1$
#30000
0"
#35000
b101 !
b101 %
1"
#36000
b1011 &
#40000
0"
#45000
b1011 !
b1011 %
1"
#46000
b110 &
0$
#50000
0"
#55000
b110 !
b110 %
1"
