day3/mux4to1.v
module mux4to1(
    input in0, in1, in2, in3,
    input [1:0] sel,
    output reg out
    );

    always @(*) begin
        case(sel)
            2'b00:out = in0;    
            2'b01:out = in1;    
            2'b10:out = in2;    
            2'b11:out = in3;
            default: out = 0;    
        endcase
    end
endmodule

day3/mux4to1_tb.v
// mux4to1_tb.v
`timescale 1ns/1ps

module mux4to1_tb;
    reg  in0, in1, in2, in3;
    reg  [1:0] sel;
    wire out;

    mux4to1 uut (
        .in0(in0), .in1(in1), .in2(in2), .in3(in3),
        .sel(sel),
        .out(out)
    );

    task check(input tin0, input tin1, input tin2, input tin3, input [1:0] tsel, input expected);
        begin
            in0 = tin0; in1 = tin1; in2 = tin2; in3 = tin3; sel = tsel;
            #10;
            if (out !== expected)
                $display("FAIL: sel=%b -> got out=%b, expected %b", tsel, out, expected);
            else
                $display("PASS: sel=%b -> out=%b", tsel, out);
        end
    endtask

    initial begin
        $dumpfile("mux4to1.vcd");
        $dumpvars(0, mux4to1_tb);

        // in0=1, in1=0, in2=1, in3=0 -- fixed pattern, sweep sel through all 4 values
        check(1, 0, 1, 0, 2'b00, 1); // sel=00 -> should pick in0 (1)
        check(1, 0, 1, 0, 2'b01, 0); // sel=01 -> should pick in1 (0)
        check(1, 0, 1, 0, 2'b10, 1); // sel=10 -> should pick in2 (1)
        check(1, 0, 1, 0, 2'b11, 0); // sel=11 -> should pick in3 (0)

        // different data pattern, same sweep, catches a mux that's accidentally hardwired to one input
        check(0, 1, 0, 1, 2'b00, 0);
        check(0, 1, 0, 1, 2'b01, 1);
        check(0, 1, 0, 1, 2'b10, 0);
        check(0, 1, 0, 1, 2'b11, 1);

        $finish;
    end
endmodule

day3/mux4to1.vcd
$date
	Thu Sep 10 14:22:55 2026
$end
$version
	Icarus Verilog
$end
$timescale
	1ps
$end
$scope module mux4to1_tb $end
$var wire 1 ! out $end
$var reg 1 " in0 $end
$var reg 1 # in1 $end
$var reg 1 $ in2 $end
$var reg 1 % in3 $end
$var reg 2 & sel [1:0] $end
$scope module uut $end
$var wire 1 " in0 $end
$var wire 1 # in1 $end
$var wire 1 $ in2 $end
$var wire 1 % in3 $end
$var wire 2 ' sel [1:0] $end
$var reg 1 ! out $end
$upscope $end
$scope task check $end
$var reg 1 ( expected $end
$var reg 1 ) tin0 $end
$var reg 1 * tin1 $end
$var reg 1 + tin2 $end
$var reg 1 , tin3 $end
$var reg 2 - tsel [1:0] $end
$upscope $end
$upscope $end
$enddefinitions $end
$comment Show the parameter values. $end
$dumpall
$end
#0
$dumpvars
b0 -
0,
1+
0*
1)
1(
b0 '
b0 &
0%
1$
0#
1"
1!
$end
#10000
0!
b1 &
b1 '
0(
b1 -
#20000
1!
b10 &
b10 '
1(
b10 -
#30000
0!
b11 &
b11 '
0(
b11 -
#40000
b0 &
b0 '
1%
0$
1#
0"
b0 -
1,
0+
1*
0)
#50000
1!
b1 &
b1 '
1(
b1 -
#60000
0!
b10 &
b10 '
0(
b10 -
#70000
1!
b11 &
b11 '
1(
b11 -
