day5/trafficlight.v
module trafficlight(
    input clk,
    input rst,    // synchronous reset to GREEN
    output [1:0] light   // 2'b00 = GREEN, 2'b01 = YELLOW, 2'b10 = RED
);
    parameter GREEN = 0, YELLOW = 1, RED = 2;
    reg [1:0] state, next_state, counter;

    always @(*) begin
        next_state = state;
        case(state) 
            RED: if (counter >= 2) next_state = GREEN;
            YELLOW: if (counter >= 1) next_state = RED;
            GREEN: if (counter >= 3) next_state = YELLOW;
        endcase
    end

    always @(posedge clk) begin
        if (rst) begin 
            state <= GREEN;
            counter <= 0;
        end
        else begin
            state <= next_state;
            if (state == next_state) counter <= counter + 1;
            else counter <= 1;
        end
    end

    assign light = state;

endmodule

day5/trafficlight_tb.v
// trafficlight_tb.v
`timescale 1ns/1ps

module trafficlight_tb;
    reg  clk, rst;
    wire [1:0] light;

    trafficlight uut (
        .clk(clk),
        .rst(rst),
        .light(light)
    );

    always #5 clk = ~clk;

    // helper to name the light state for readable output
    function [55:0] light_name;
        input [1:0] l;
        case(l)
            2'b00: light_name = "GREEN";
            2'b01: light_name = "YELLOW";
            2'b10: light_name = "RED";
            default: light_name = "UNKNOWN";
        endcase
    endfunction

    integer i;

    initial begin
        $dumpfile("trafficlight.vcd");
        $dumpvars(0, trafficlight_tb);

        clk = 0; rst = 1;
        @(posedge clk); #1;
        rst = 0;

        // run for 30 cycles, print light state each cycle
        // expected pattern: GREEN x3, YELLOW x1, RED x2, GREEN x3 ...
        for (i = 0; i < 30; i = i + 1) begin
            @(posedge clk); #1;
            $display("cycle %0d: %s (%b)", i, light_name(light), light);
        end

        // test that reset actually works mid-sequence
        rst = 1;
        @(posedge clk); #1;
        $display("after reset: %s (should be GREEN)", light_name(light));
        rst = 0;

        // run 6 more cycles and check pattern restarts cleanly
        for (i = 0; i < 20; i = i + 1) begin
            @(posedge clk); #1;
            $display("post-reset cycle %0d: %s", i, light_name(light));
        end

        $finish;
    end
endmodule

day5/trafficlight.vcd
$date
	Fri Sep 11 20:09:19 2026
$end
$version
	Icarus Verilog
$end
$timescale
	1ps
$end
$scope module trafficlight_tb $end
$var wire 2 ! light [1:0] $end
$var reg 1 " clk $end
$var reg 1 # rst $end
$var integer 32 $ i [31:0] $end
$scope function light_name $end
$var reg 2 % l [1:0] $end
$upscope $end
$scope module uut $end
$var wire 1 " clk $end
$var wire 2 & light [1:0] $end
$var wire 1 # rst $end
$var parameter 32 ' GREEN $end
$var parameter 32 ( RED $end
$var parameter 32 ) YELLOW $end
$var reg 2 * counter [1:0] $end
$var reg 2 + next_state [1:0] $end
$var reg 2 , state [1:0] $end
$upscope $end
$upscope $end
$enddefinitions $end
$comment Show the parameter values. $end
$dumpall
b1 )
b10 (
b0 '
$end
#0
$dumpvars
bx ,
bx +
bx *
bx &
bx %
bx $
1#
0"
bx !
$end
#5000
b0 +
b0 *
b0 !
b0 &
b0 ,
1"
#6000
b0 $
0#
#10000
0"
#15000
b1 *
1"
#16000
b1 $
b0 %
#20000
0"
#25000
b10 *
1"
#26000
b10 $
#30000
0"
#35000
b1 +
b11 *
1"
#36000
b11 $
#40000
0"
#45000
b10 +
b1 *
b1 !
b1 &
b1 ,
1"
#46000
b100 $
b1 %
#50000
0"
#55000
b10 !
b10 &
b10 ,
1"
#56000
b101 $
b10 %
#60000
0"
#65000
b0 +
b10 *
1"
#66000
b110 $
#70000
0"
#75000
b1 *
b0 !
b0 &
b0 ,
1"
#76000
b111 $
b0 %
#80000
0"
#85000
b10 *
1"
#86000
b1000 $
#90000
0"
#95000
b1 +
b11 *
1"
#96000
b1001 $
#100000
0"
#105000
b10 +
b1 *
b1 !
b1 &
b1 ,
1"
#106000
b1010 $
b1 %
#110000
0"
#115000
b10 !
b10 &
b10 ,
1"
#116000
b1011 $
b10 %
#120000
0"
#125000
b0 +
b10 *
1"
#126000
b1100 $
#130000
0"
#135000
b1 *
b0 !
b0 &
b0 ,
1"
#136000
b1101 $
b0 %
#140000
0"
#145000
b10 *
1"
#146000
b1110 $
#150000
0"
#155000
b1 +
b11 *
1"
#156000
b1111 $
#160000
0"
#165000
b10 +
b1 *
b1 !
b1 &
b1 ,
1"
#166000
b10000 $
b1 %
#170000
0"
#175000
b10 !
b10 &
b10 ,
1"
#176000
b10001 $
b10 %
#180000
0"
#185000
b0 +
b10 *
1"
#186000
b10010 $
#190000
0"
#195000
b1 *
b0 !
b0 &
b0 ,
1"
#196000
b10011 $
b0 %
#200000
0"
#205000
b10 *
1"
#206000
b10100 $
#210000
0"
#215000
b1 +
b11 *
1"
#216000
b10101 $
#220000
0"
#225000
b10 +
b1 *
b1 !
b1 &
b1 ,
1"
#226000
b10110 $
b1 %
#230000
0"
#235000
b10 !
b10 &
b10 ,
1"
#236000
b10111 $
b10 %
#240000
0"
#245000
b0 +
b10 *
1"
#246000
b11000 $
#250000
0"
#255000
b1 *
b0 !
b0 &
b0 ,
1"
#256000
b11001 $
b0 %
#260000
0"
#265000
b10 *
1"
#266000
b11010 $
#270000
0"
#275000
b1 +
b11 *
1"
#276000
b11011 $
#280000
0"
#285000
b10 +
b1 *
b1 !
b1 &
b1 ,
1"
#286000
b11100 $
b1 %
#290000
0"
#295000
b10 !
b10 &
b10 ,
1"
#296000
b11101 $
b10 %
#300000
0"
#305000
b0 +
b10 *
1"
#306000
1#
b11110 $
#310000
0"
#315000
b0 *
b0 !
b0 &
b0 ,
1"
#316000
b0 $
0#
b0 %
#320000
0"
#325000
b1 *
1"
#326000
b1 $
#330000
0"
#335000
b10 *
1"
#336000
b10 $
#340000
0"
#345000
b1 +
b11 *
1"
#346000
b11 $
#350000
0"
#355000
b10 +
b1 *
b1 !
b1 &
b1 ,
1"
#356000
b100 $
b1 %
#360000
0"
#365000
b10 !
b10 &
b10 ,
1"
#366000
b101 $
b10 %
#370000
0"
#375000
b0 +
b10 *
1"
#376000
b110 $
#380000
0"
#385000
b1 *
b0 !
b0 &
b0 ,
1"
#386000
b111 $
b0 %
#390000
0"
#395000
b10 *
1"
#396000
b1000 $
#400000
0"
#405000
b1 +
b11 *
1"
#406000
b1001 $
#410000
0"
#415000
b10 +
b1 *
b1 !
b1 &
b1 ,
1"
#416000
b1010 $
b1 %
#420000
0"
#425000
b10 !
b10 &
b10 ,
1"
#426000
b1011 $
b10 %
#430000
0"
#435000
b0 +
b10 *
1"
#436000
b1100 $
#440000
0"
#445000
b1 *
b0 !
b0 &
b0 ,
1"
#446000
b1101 $
b0 %
#450000
0"
#455000
b10 *
1"
#456000
b1110 $
#460000
0"
#465000
b1 +
b11 *
1"
#466000
b1111 $
#470000
0"
#475000
b10 +
b1 *
b1 !
b1 &
b1 ,
1"
#476000
b10000 $
b1 %
#480000
0"
#485000
b10 !
b10 &
b10 ,
1"
#486000
b10001 $
b10 %
#490000
0"
#495000
b0 +
b10 *
1"
#496000
b10010 $
#500000
0"
#505000
b1 *
b0 !
b0 &
b0 ,
1"
#506000
b10011 $
b0 %
#510000
0"
#515000
b10 *
1"
#516000
b10100 $
