day2/adder4.v
module adder(input a, input b, output cout, output sum, input cin);
    assign {cout, sum} = a + b + cin;
endmodule

module adder4(input [3:0]a, input [3:0]b, input cin, output [3:0]sum, output cout);
    wire cout0, cout1, cout2;
    adder adder1(.a(a[0]), .b(b[0]), .cin(cin), .cout(cout0), .sum(sum[0]));
    adder adder2(.a(a[1]), .b(b[1]), .cin(cout0), .cout(cout1), .sum(sum[1]));
    adder adder3(.a(a[2]), .b(b[2]), .cin(cout1), .cout(cout2), .sum(sum[2]));
    adder adder4(.a(a[3]), .b(b[3]), .cin(cout2), .cout(cout), .sum(sum[3]));
endmodule

day2/adder4_tb.v
// adder4_tb.v
`timescale 1ns/1ps

module adder4_tb;
    reg  [3:0] a, b;
    reg        cin;
    wire [3:0] sum;
    wire       cout;

    adder4 uut (
        .a(a),
        .b(b),
        .cin(cin),
        .sum(sum),
        .cout(cout)
    );

    task check(input [3:0] ta, input [3:0] tb, input tcin);
        reg [4:0] expected;
        begin
            a = ta; b = tb; cin = tcin;
            #10;
            expected = ta + tb + tcin;
            if ({cout, sum} !== expected)
                $display("FAIL: a=%b b=%b cin=%b -> got {cout,sum}=%b%b, expected %b",
                          ta, tb, tcin, cout, sum, expected);
            else
                $display("PASS: a=%b b=%b cin=%b -> sum=%b cout=%b", ta, tb, tcin, sum, cout);
        end
    endtask

    initial begin
        $dumpfile("adder4.vcd");
        $dumpvars(0, adder4_tb);

        check(4'b0001, 4'b0001, 1'b0); // simple add, no carry
        check(4'b0111, 4'b0001, 1'b0); // internal carry propagation
        check(4'b1111, 4'b0001, 1'b0); // full ripple, cout should go high
        check(4'b1111, 4'b1111, 1'b1); // max values + carry-in, stress overflow
        check(4'b0000, 4'b0000, 1'b1); // cin alone should propagate through
        check(4'b1010, 4'b0101, 1'b0); // no carry anywhere
        check(4'b1000, 4'b1000, 1'b0); // carry only from top bit

        $finish;
    end
endmodule

day2/adder4.vcd
$date
	Wed Sep  9 20:51:17 2026
$end
$version
	Icarus Verilog
$end
$timescale
	1ps
$end
$scope module adder4_tb $end
$var wire 4 ! sum [3:0] $end
$var wire 1 " cout $end
$var reg 4 # a [3:0] $end
$var reg 4 $ b [3:0] $end
$var reg 1 % cin $end
$scope module uut $end
$var wire 4 & a [3:0] $end
$var wire 4 ' b [3:0] $end
$var wire 1 % cin $end
$var wire 4 ( sum [3:0] $end
$var wire 1 ) cout2 $end
$var wire 1 * cout1 $end
$var wire 1 + cout0 $end
$var wire 1 " cout $end
$scope module adder1 $end
$var wire 1 , a $end
$var wire 1 - b $end
$var wire 1 % cin $end
$var wire 1 . sum $end
$var wire 1 + cout $end
$upscope $end
$scope module adder2 $end
$var wire 1 / a $end
$var wire 1 0 b $end
$var wire 1 + cin $end
$var wire 1 1 sum $end
$var wire 1 * cout $end
$upscope $end
$scope module adder3 $end
$var wire 1 2 a $end
$var wire 1 3 b $end
$var wire 1 * cin $end
$var wire 1 4 sum $end
$var wire 1 ) cout $end
$upscope $end
$scope module adder4 $end
$var wire 1 5 a $end
$var wire 1 6 b $end
$var wire 1 ) cin $end
$var wire 1 7 sum $end
$var wire 1 " cout $end
$upscope $end
$upscope $end
$scope task check $end
$var reg 5 8 expected [4:0] $end
$var reg 4 9 ta [3:0] $end
$var reg 4 : tb [3:0] $end
$var reg 1 ; tcin $end
$upscope $end
$upscope $end
$enddefinitions $end
$comment Show the parameter values. $end
$dumpall
$end
#0
$dumpvars
0;
b1 :
b1 9
bx 8
07
06
05
04
03
02
11
00
0/
0.
1-
1,
1+
0*
0)
b10 (
b1 '
b1 &
0%
b1 $
b1 #
0"
b10 !
$end
#10000
17
1)
01
1*
b1000 !
b1000 (
04
1/
12
b111 #
b111 &
b111 9
b10 8
#20000
b0 !
b0 (
07
1"
15
b1111 #
b1111 &
b1111 9
b1000 8
#30000
11
14
17
b1111 !
b1111 (
1.
10
13
16
1%
b1111 $
b1111 '
1;
b1111 :
b10000 8
#40000
01
04
b1 !
b1 (
07
0+
0*
0)
0"
0-
00
03
06
0,
0/
02
05
b0 $
b0 '
b0 #
b0 &
b0 :
b0 9
b11111 8
#50000
14
11
b1111 !
b1111 (
17
1-
13
1/
15
0%
b101 $
b101 '
b1010 #
b1010 &
0;
b101 :
b1010 9
b1 8
#60000
0.
04
07
1"
b0 !
b0 (
01
0-
03
16
0/
b1000 $
b1000 '
b1000 #
b1000 &
b1000 :
b1000 9
b1111 8
#70000
b10000 8
